easytuio/__init__.py
easytuio/client.py
easytuio/messages.py
easytuio/profiles.py
easytuio/utils.py
easytuio-0.1.1.dist-info/METADATA
easytuio-0.1.1.dist-info/WHEEL
easytuio-0.1.1.dist-info/top_level.txt
easytuio-0.1.1.dist-info/RECORD
