Metadata-Version: 2.1
Name: easytuio
Version: 0.1.1
Summary: A Python library for handling TUIO messages
Author-email: Vishnu <vishnu@acemetrics.com>
License: MIT License
Project-URL: Documentation, https://gitlab.com/acemetrics-technologies/easytuio#README
Project-URL: Source, https://gitlab.com/acemetrics-technologies/easytuio
Project-URL: Tracker, https://gitlab.com/acemetrics-technologies/easytuio/-/issues
Keywords: TUIO,multi-touch,tangible interaction,OSC
Classifier: Programming Language :: Python :: 3
Classifier: License :: OSI Approved :: MIT License
Classifier: Operating System :: OS Independent
Requires-Dist: python-osc
